README.rst
setup.cfg
setup.py
imps/__init__.py
imps/core.py
imps/rebuilders.py
imps/shell.py
imps/stdlib.py
imps/strings.py
imps.egg-info/PKG-INFO
imps.egg-info/SOURCES.txt
imps.egg-info/dependency_links.txt
imps.egg-info/entry_points.txt
imps.egg-info/pbr.json
imps.egg-info/requires.txt
imps.egg-info/top_level.txt