Metadata-Version: 1.1
Name: imps
Version: 0.2.5
Summary: Python utility to sort Python imports
Home-page: https://github.com/bootandy/imps
Author: Andy Boot
Author-email: bootandy@gmail.com
License: Apache
Keywords: Refactoring,Imports
Platform: UNKNOWN
Classifier: Intended Audience :: Developers
Classifier: Natural Language :: English
Classifier: Environment :: Console
Classifier: Programming Language :: Python :: 2.7
Classifier: Topic :: Software Development :: Libraries
Classifier: Topic :: Utilities
